rocketsled/__init__.py
rocketsled/acq.py
rocketsled/control.py
rocketsled/defaults.yaml
rocketsled/task.py
rocketsled/utils.py
rocketsled/examples/__init__.py
rocketsled/examples/basic.py
rocketsled/examples/batch.py
rocketsled/examples/complex.py
rocketsled/tests/__init__.py
rocketsled/tests/deserialize_func.py
rocketsled/tests/test_task.py
rocketsled/tests/test_utils.py
rocketsled-1.1.0.20211129.dist-info/LICENSE.txt
rocketsled-1.1.0.20211129.dist-info/METADATA
rocketsled-1.1.0.20211129.dist-info/WHEEL
rocketsled-1.1.0.20211129.dist-info/top_level.txt
rocketsled-1.1.0.20211129.dist-info/RECORD
