Metadata-Version: 2.1
Name: rocketsled
Version: 1.1.0.20211129
Summary: Black box optimization with Fireworks workflows, on rails
Home-page: https://github.com/hackingmaterials/rocktsled
Author: Alex Dunn
Author-email: ardunn@lbl.gov
License: modified BSD
Keywords: black-box-optimization optimization workflows
Platform: UNKNOWN
Classifier: Development Status :: 3 - Alpha
Classifier: Intended Audience :: Science/Research
Classifier: Intended Audience :: Information Technology
Classifier: License :: OSI Approved :: MIT License
Classifier: Natural Language :: English
Classifier: Programming Language :: Python :: 3 :: Only
Classifier: Topic :: Scientific/Engineering :: Chemistry
Classifier: Topic :: Scientific/Engineering :: Physics
Classifier: Topic :: Scientific/Engineering
Classifier: Topic :: Other/Nonlisted Topic
Classifier: Operating System :: OS Independent
Requires-Dist: numpy (==1.17.2)
Requires-Dist: scikit-learn (==1.0.1)
Requires-Dist: scipy (==1.7.1)
Requires-Dist: pymongo (==3.10.1)
Requires-Dist: fireworks (==1.9.7)
Requires-Dist: matplotlib (==3.2.1)
Requires-Dist: joblib (==1.0.1)
